gcm.py
GCMlib-1.0.4.dist-info/LICENSE
GCMlib-1.0.4.dist-info/METADATA
GCMlib-1.0.4.dist-info/WHEEL
GCMlib-1.0.4.dist-info/top_level.txt
GCMlib-1.0.4.dist-info/RECORD
