Metadata-Version: 2.1
Name: GCMlib
Version: 1.0.4
Summary: A minimalistic and simple encryption library. For encrypting data using AES GCM mode.
Home-page: https://github.com/therealOri/GCMlib
Author: therealOri
Author-email: therealOri@duck.com
License: GPL-3.0
License-File: LICENSE
Requires-Dist: alive-progress
Requires-Dist: pycryptodome
Requires-Dist: argon2-cffi
